julian.py
magvar.cpython-39-darwin.so
magvar-1.0.0.dist-info/LICENSE
magvar-1.0.0.dist-info/METADATA
magvar-1.0.0.dist-info/WHEEL
magvar-1.0.0.dist-info/top_level.txt
magvar-1.0.0.dist-info/RECORD
