Metadata-Version: 2.1
Name: magvar
Version: 1.0.0
Summary: Magnetic variation (aka declination) for aviation navigation
Author: Terence Way
Author-email: Terence Way <terry@wayforward.net>
Project-URL: Homepage, https://www.wayforward.net/magvar/
Classifier: License :: OSI Approved :: GNU Library or Lesser General Public License (LGPL)
Classifier: Topic :: Scientific/Engineering :: GIS
Classifier: Intended Audience :: Developers
Classifier: Intended Audience :: Science/Research
Classifier: Development Status :: 4 - Beta
Requires-Python: >=3.1
License-File: LICENSE
